bhqmain-4.2.1.dist-info/licenses/LICENSE
bhqmain4/LICENSE
bhqmain4/__init__.py
bhqmain4/_main.py
bhqmain-4.2.1.dist-info/METADATA
bhqmain-4.2.1.dist-info/WHEEL
bhqmain-4.2.1.dist-info/top_level.txt
bhqmain-4.2.1.dist-info/RECORD
