Metadata-Version: 2.4
Name: bhqmain
Version: 4.2.1
Summary: Initialization framework for Blender extensions
Author-email: Ivan Perevala <ivan95perevala@gmail.com>
License-Expression: MIT
Project-URL: Homepage, https://github.com/ivan-perevala/lib_bhqmain
Project-URL: Issues, https://github.com/ivan-perevala/lib_bhqmain/issues
Project-URL: Documentation, https://lib-bhqmain.readthedocs.io/4.2.1/
Keywords: framework,singleton,chunk
Classifier: Programming Language :: Python :: 3
Classifier: Operating System :: OS Independent
Requires-Python: >=3.11
License-File: LICENSE
Dynamic: license-file
